rhcloud.py
setup.py
rhcloud.egg-info/PKG-INFO
rhcloud.egg-info/SOURCES.txt
rhcloud.egg-info/dependency_links.txt
rhcloud.egg-info/top_level.txt