Metadata-Version: 1.0
Name: rhcloud
Version: 0.0.1
Summary: Just for test first
Home-page: UNKNOWN
Author: Fris
Author-email: fris@live.com
License: UNKNOWN
Platform: UNKNOWN
